gtbmm/__init__.py
gtbmm/exceptions.py
python_gtbmm-0.1.dist-info/DESCRIPTION.rst
python_gtbmm-0.1.dist-info/METADATA
python_gtbmm-0.1.dist-info/metadata.json
python_gtbmm-0.1.dist-info/RECORD
python_gtbmm-0.1.dist-info/top_level.txt
python_gtbmm-0.1.dist-info/WHEEL
