Metadata-Version: 2.0
Name: python-gtbmm
Version: 0.1
Summary: A Guaranty Trust Bank Mobile Money interface library
Home-page: http://pypi.python.org/pypi/python-gtbmm/
Author: Tim Akinbo
Author-email: takinbo@timbaobjects.com
License: LICENSE
Platform: UNKNOWN
Requires-Dist: lxml (>=3.3.5)
Requires-Dist: pytest (>=2.6.0)
Requires-Dist: requests (>=2.3.0)
